predictit/__init__.py
predictit/_helpers.py
predictit/_main_loop.py
predictit/_result_classes.py
predictit/analyze.py
predictit/best_params.py
predictit/configuration.py
predictit/evaluate_predictions.py
predictit/gui_start.py
predictit/main.py
predictit/misc.py
predictit/models/__init__.py
predictit/models/autoreg_LNU.py
predictit/models/average.py
predictit/models/conjugate_gradient.py
predictit/models/levenberg_marquardt.py
predictit/models/regression.py
predictit/models/sklearn_regression.py
predictit/models/statsmodels_autoregressive.py
predictit/models/tensorflow.py
predictit/models/models_functions/__init__.py
predictit/models/models_functions/models_functions.py
predictit-2.0.7.dist-info/LICENSE
predictit-2.0.7.dist-info/METADATA
predictit-2.0.7.dist-info/WHEEL
predictit-2.0.7.dist-info/top_level.txt
predictit-2.0.7.dist-info/RECORD
