Metadata-Version: 2.1
Name: predictit
Version: 2.0.7
Summary: Library/framework for making time series predictions with help of AutoML tools.
Home-page: https://github.com/Malachov/predictit
Author: Daniel Malachov
Author-email: malachovd@seznam.cz
License: mit
Platform: any
Classifier: Programming Language :: Python
Classifier: Development Status :: 3 - Alpha
Classifier: Programming Language :: Python :: 3.7
Classifier: Programming Language :: Python :: 3.8
Classifier: Programming Language :: Python :: 3.9
Classifier: Natural Language :: English
Classifier: Environment :: Other Environment
Classifier: License :: OSI Approved :: MIT License
Classifier: Operating System :: OS Independent
Classifier: Topic :: Scientific/Engineering :: Artificial Intelligence
Classifier: Topic :: Software Development :: Libraries :: Python Modules
Classifier: Topic :: Software Development :: Libraries :: Application Frameworks
Classifier: Intended Audience :: Science/Research
Classifier: Intended Audience :: Developers
Classifier: Intended Audience :: Education
License-File: LICENSE
Requires-Dist: mydatapreprocessing (==2.0.10)
Requires-Dist: mylogging (==3.0.12)
Requires-Dist: mypythontools (==0.0.78)
Requires-Dist: numpy
Requires-Dist: pandas
Requires-Dist: eel
Requires-Dist: scipy
Requires-Dist: statsmodels
Requires-Dist: sklearn
Requires-Dist: tabulate
Requires-Dist: matplotlib
Requires-Dist: seaborn
Requires-Dist: IPython
Requires-Dist: typing-extensions
